greenland/runtime/.gitignore
greenland/runtime/__init__.py
greenland/runtime/__version__.py
greenland/runtime/control.py
greenland/runtime/env_vars.py
greenland/runtime/events.py
greenland/runtime/module_aware_objects.py
greenland/runtime/program_info.py
greenland/runtime/py.typed
greenland/runtime/start.py
greenland/runtime/version.py
greenland/runtime/app/greenland_debug.py
greenland/runtime/bin/greenland_debug.py
greenland/runtime/logging/__init__.py
greenland/runtime/logging/base.py
greenland/runtime/logging/per_module.py
greenland_runtime-0.0.3.dist-info/METADATA
greenland_runtime-0.0.3.dist-info/WHEEL
greenland_runtime-0.0.3.dist-info/entry_points.txt
greenland_runtime-0.0.3.dist-info/licenses/LICENSE.txt
greenland_runtime-0.0.3.dist-info/RECORD
