Metadata-Version: 2.3
Name: greenland-runtime
Version: 0.0.3
Summary: A common runtime for greenland projects
Project-URL: Homepage, https://codeberg.org/m-e-leypold/greenland-runtime
Project-URL: Documentation, https://codeberg.org/m-e-leypold/greenland-runtime#readme
Project-URL: Issues, https://codeberg.org/m-e-leypold/greenland-runtime/issues
Project-URL: Source, https://codeberg.org/m-e-leypold/greenland-runtime
Author: M E Leypold
Author-email: M E Leypold <pythonista-4sda212@m-e-leypold.de>
License: GPL-3.0-or-later
Classifier: Development Status :: 4 - Beta
Classifier: Programming Language :: Python
Classifier: Programming Language :: Python :: 3.9
Classifier: Programming Language :: Python :: 3.10
Classifier: Programming Language :: Python :: 3.11
Classifier: Programming Language :: Python :: 3.12
Classifier: Programming Language :: Python :: Implementation :: CPython
Classifier: Programming Language :: Python :: Implementation :: PyPy
Requires-Python: >=3.8
Requires-Dist: docopt-ng
Requires-Dist: greenland-base
Requires-Dist: packaging
